<partnerships>
	<partner name="OpenAS2A"
		as2_id="OpenAS2A"
		x509_alias="openas2a"
                content_transfer_encoding="8bit"
		email="OpenAS2 A email"/>
	<partner name="OpenAS2B"
		as2_id="OpenAS2B"
		x509_alias="openas2b"
                content_transfer_encoding="8bit"
		email="OpenAS2 A email"/>	

	<partnership name="OpenAS2A-OpenAS2B">
		<sender name="OpenAS2A"/>
		<receiver name="OpenAS2B"/>
		<attribute name="protocol" value="as2"/>
		<attribute name="subject" value="From OpenAS2A to OpenAS2B"/>
		<attribute name="as2_url" value="http://localhost:10090"/>
		<attribute name="as2_mdn_to" value="http://localhost:10080"/>
		<attribute name="as2_mdn_options" value="signed-receipt-protocol=optional, pkcs7-signature; signed-receipt-micalg=optional, SHA1"/>
		<attribute name="encrypt" value="3DES"/>
		<attribute name="sign" value="MD5"/>
	</partnership>
	
	<partnership name="OpenAS2B-OpenAS2A">
		<sender name="OpenAS2B"/>
		<receiver name="OpenAS2A"/>
		<attribute name="protocol" value="as2"/>
		<attribute name="subject" value="From OpenAS2B to OpenAS2A"/>
		<attribute name="as2_url" value="http://localhost:10091"/>
		<attribute name="as2_mdn_to" value="http://localhost:10081"/>
		<attribute name="as2_mdn_options" value="signed-receipt-protocol=optional, pkcs7-signature; signed-receipt-micalg=optional, SHA1"/>
		<attribute name="encrypt" value="3DES"/>
		<attribute name="sign" value="SHA1"/>
	</partnership>
</partnerships>

